pytalk/__init__.py
MultiTalk-1.0.2.dist-info/LICENSE.txt
MultiTalk-1.0.2.dist-info/METADATA
MultiTalk-1.0.2.dist-info/WHEEL
MultiTalk-1.0.2.dist-info/top_level.txt
MultiTalk-1.0.2.dist-info/RECORD
