Metadata-Version: 2.1
Name: MultiTalk
Version: 1.0.2
Summary: UNKNOWN
Home-page: UNKNOWN
Author: sonyakun
License: UNKNOWN
Platform: UNKNOWN
License-File: LICENSE.txt
Requires-Dist: requests
Requires-Dist: asyncio
